python_ey_pyc/__init__.py
python_ey_pyc/Maths/__init__.py
python_ey_pyc/Maths/Library/__init__.py
python_ey_pyc/Maths/math_lib/__init__.py
python_ey_pyc/my_strings/__init__.py
python_ey_pyc-0.1.dist-info/licenses/licence.txt
python_ey_pyc-0.1.dist-info/METADATA
python_ey_pyc-0.1.dist-info/WHEEL
python_ey_pyc-0.1.dist-info/top_level.txt
python_ey_pyc-0.1.dist-info/RECORD
