Metadata-Version: 2.4
Name: python_ey_pyc
Version: 0.1
Summary: This Package has both maths & text library APIs
Author: Suresh Maha Rajashekar
Author-email: sureshmaha@greatpythonlearning.com
License-File: licence.txt
Dynamic: author
Dynamic: author-email
Dynamic: license-file
Dynamic: summary
